{
  "_class": "text",
  "attributedString": {
    "_class": "attributedString",
    "attributes": [
      {
        "_class": "stringAttribute",
        "attributes": {
          "MSAttributedStringColorAttribute": {
            "_class": "color",
            "alpha": 1,
            "blue": 0.4,
            "green": 0.4,
            "red": 0.4
          },
          "MSAttributedStringFontAttribute": {
            "_class": "fontDescriptor",
            "attributes": {
              "name": "Gibson-SemiBold",
              "size": 40
            }
          },
          "kerning": 3.297619166666662,
          "paragraphStyle": {
            "_class": "paragraphStyle",
            "alignment": 2,
            "maximumLineHeight": 20,
            "minimumLineHeight": 20
          },
          "textStyleVerticalAlignmentKey": 1
        },
        "length": 6,
        "location": 0
      }
    ],
    "string": "Kz2fS7"
  },
  "automaticallyDrawOnUnderlyingPath": false,
  "booleanOperation": -1,
  "clippingMaskMode": 0,
  "do_objectID": "C13DDC89-98C1-4F98-AB3D-BDCAC1366FA0",
  "dontSynchroniseWithSymbol": false,
  "exportOptions": {
    "_class": "exportOptions",
    "do_objectID": "BDA32064-0BF3-4974-A1FD-2DFD55BBB055",
    "exportFormats": [
    ],
    "includedLayerIds": [
    ],
    "layerOptions": 0,
    "shouldTrim": false
  },
  "frame": {
    "_class": "rect",
    "constrainProportions": false,
    "do_objectID": "7E1361D8-BE09-48D2-BDD5-C66CEE565EA1",
    "height": 84,
    "width": 267,
    "x": 54,
    "y": 395
  },
  "glyphBounds": "{{61, -9}, {143, 30}}",
  "hasClippingMask": false,
  "isFixedToViewport": false,
  "isFlippedHorizontal": false,
  "isFlippedVertical": false,
  "isLocked": false,
  "isVisible": true,
  "layerListExpandedType": 0,
  "lineSpacingBehaviour": 2,
  "name": "Kz2fS7",
  "nameIsFixed": false,
  "resizingConstraint": 47,
  "resizingType": 0,
  "rotation": 0,
  "shouldBreakMaskChain": false,
  "style": {
    "_class": "style",
    "do_objectID": "E27F41F4-842C-4C2B-9633-21D69790D197",
    "endMarkerType": 0,
    "miterLimit": 10,
    "startMarkerType": 0,
    "textStyle": {
      "_class": "textStyle",
      "do_objectID": "12610D45-0F29-4DC5-BC70-C7C0B7B65BC8",
      "encodedAttributes": {
        "MSAttributedStringColorAttribute": {
          "_class": "color",
          "alpha": 1,
          "blue": 0.4,
          "green": 0.4,
          "red": 0.4
        },
        "MSAttributedStringFontAttribute": {
          "_class": "fontDescriptor",
          "attributes": {
            "name": "Gibson-SemiBold",
            "size": 40
          }
        },
        "kerning": 3.297619166666662,
        "paragraphStyle": {
          "_class": "paragraphStyle",
          "alignment": 2,
          "maximumLineHeight": 20,
          "minimumLineHeight": 20
        },
        "textStyleVerticalAlignmentKey": 1
      },
      "verticalAlignment": 1
    },
    "windingRule": 1
  },
  "textBehaviour": 2
}