{
  "_class": "group",
  "booleanOperation": -1,
  "clippingMaskMode": 0,
  "do_objectID": "6B5838C9-E2D0-4726-8F93-64D053B97BBB",
  "exportOptions": {
    "_class": "exportOptions",
    "do_objectID": "257BCBA8-4D8B-4D6B-88CD-EB9097DE6ED4",
    "exportFormats": [
    ],
    "includedLayerIds": [
    ],
    "layerOptions": 0,
    "shouldTrim": false
  },
  "frame": {
    "_class": "rect",
    "constrainProportions": false,
    "do_objectID": "0AC88035-819C-47F9-87A0-58D8E53B5613",
    "height": 42,
    "width": 31,
    "x": 281,
    "y": 54
  },
  "groupLayout": {
    "_class": "MSImmutableFreeformGroupLayout",
    "do_objectID": "B9B4FFD4-CAD9-4FFC-A758-F1E90E9F71AD"
  },
  "hasClickThrough": false,
  "hasClippingMask": false,
  "isFixedToViewport": false,
  "isFlippedHorizontal": false,
  "isFlippedVertical": false,
  "isLocked": true,
  "isVisible": true,
  "layerListExpandedType": 0,
  "layers": [
    {
      "class": "rectangle",
      "id": "6720FCE1-1F4E-421B-9D8C-23B2C2EC028E"
    },
    {
      "class": "text",
      "id": "35473B8C-10F4-41E2-87EE-E6A2C0A17D09"
    }
  ],
  "name": "Alphabet",
  "nameIsFixed": false,
  "resizingConstraint": 63,
  "resizingType": 0,
  "rotation": 0,
  "shouldBreakMaskChain": false,
  "style": {
    "_class": "style",
    "do_objectID": "523A396C-2AF2-4573-A227-8D8ABC4883D3",
    "endMarkerType": 0,
    "miterLimit": 10,
    "startMarkerType": 0,
    "windingRule": 1
  }
}