{
  "_class": "shapePath",
  "booleanOperation": -1,
  "clippingMaskMode": 0,
  "do_objectID": "CFC5BE71-EA9E-4431-BD34-3982434D80D3",
  "edited": true,
  "exportOptions": {
    "_class": "exportOptions",
    "do_objectID": "FAE6F6A6-C81C-404E-BA7A-17DE78FB9190",
    "exportFormats": [
    ],
    "includedLayerIds": [
    ],
    "layerOptions": 0,
    "shouldTrim": false
  },
  "frame": {
    "_class": "rect",
    "constrainProportions": false,
    "do_objectID": "6929FEE0-088A-46C5-BF36-7E4501C4A1F3",
    "height": 14.39994791666667,
    "width": 14.35911458333333,
    "x": 3.190979166666669,
    "y": 3.200093750000001
  },
  "hasClippingMask": false,
  "isClosed": true,
  "isFixedToViewport": false,
  "isFlippedHorizontal": false,
  "isFlippedVertical": false,
  "isLocked": false,
  "isVisible": true,
  "layerListExpandedType": 0,
  "name": "Path",
  "nameIsFixed": false,
  "pointRadiusBehaviour": 1,
  "points": [
    {
      "_class": "curvePoint",
      "cornerRadius": 0,
      "curveFrom": "{0.22222165799162116, 1}",
      "curveMode": 2,
      "curveTo": "{0.77777326393296942, 1}",
      "hasCurveFrom": true,
      "hasCurveTo": true,
      "point": "{0.50000253903770475, 1}"
    },
    {
      "_class": "curvePoint",
      "cornerRadius": 0,
      "curveFrom": "{0, 0.22221434539332099}",
      "curveMode": 2,
      "curveTo": "{0, 0.77777046357951241}",
      "hasCurveFrom": true,
      "hasCurveTo": true,
      "point": "{0, 0.49999746816213886}"
    },
    {
      "_class": "curvePoint",
      "cornerRadius": 0,
      "curveFrom": "{0.77777326393296942, 0}",
      "curveMode": 2,
      "curveTo": "{0.22222165799162116, 0}",
      "hasCurveFrom": true,
      "hasCurveTo": true,
      "point": "{0.50000253903770475, 0}"
    },
    {
      "_class": "curvePoint",
      "cornerRadius": 0,
      "curveFrom": "{1, 0.77777046357951241}",
      "curveMode": 2,
      "curveTo": "{1, 0.22221434539332099}",
      "hasCurveFrom": true,
      "hasCurveTo": true,
      "point": "{1, 0.49999746816213886}"
    }
  ],
  "resizingConstraint": 63,
  "resizingType": 0,
  "rotation": 0,
  "shouldBreakMaskChain": false,
  "style": {
    "_class": "style",
    "do_objectID": "69563340-13DF-46B2-86D4-8D152C98A3C2",
    "endMarkerType": 0,
    "miterLimit": 10,
    "startMarkerType": 0,
    "windingRule": 1
  }
}