{
  "_class": "group",
  "booleanOperation": -1,
  "clippingMaskMode": 0,
  "do_objectID": "44707542-2030-47B9-9FF9-B056792456A8",
  "exportOptions": {
    "_class": "exportOptions",
    "do_objectID": "7AEA2A35-B4D8-4987-9D32-83A4767050C5",
    "exportFormats": [
    ],
    "includedLayerIds": [
    ],
    "layerOptions": 0,
    "shouldTrim": false
  },
  "frame": {
    "_class": "rect",
    "constrainProportions": true,
    "do_objectID": "C2A8EE01-EB76-42A0-9683-6A8420DA01F5",
    "height": 28,
    "width": 23.8,
    "x": 1478,
    "y": 304.5
  },
  "groupLayout": {
    "_class": "MSImmutableFreeformGroupLayout",
    "do_objectID": "2F4FE214-6876-4080-AD14-5EC95527D084"
  },
  "hasClickThrough": false,
  "hasClippingMask": false,
  "isFixedToViewport": false,
  "isFlippedHorizontal": false,
  "isFlippedVertical": false,
  "isLocked": false,
  "isVisible": true,
  "layerListExpandedType": 2,
  "layers": [
    {
      "class": "shapeGroup",
      "id": "8942629E-68F5-4246-BC64-0570211E31ED"
    }
  ],
  "name": "md/trash",
  "nameIsFixed": false,
  "resizingConstraint": 63,
  "resizingType": 0,
  "rotation": 0,
  "shouldBreakMaskChain": false,
  "style": {
    "_class": "style",
    "do_objectID": "64FC842D-D492-492B-A5B3-FC2D409F873E",
    "endMarkerType": 0,
    "miterLimit": 10,
    "startMarkerType": 0,
    "windingRule": 1
  }
}