{
  "_class": "symbolInstance",
  "booleanOperation": -1,
  "clippingMaskMode": 0,
  "do_objectID": "D479152A-C2AF-4D93-BB5B-1BA6A3A95801",
  "exportOptions": {
    "_class": "exportOptions",
    "do_objectID": "C196A45E-1A49-4E86-87C0-9B12178BE251",
    "exportFormats": [
    ],
    "includedLayerIds": [
    ],
    "layerOptions": 0,
    "shouldTrim": false
  },
  "frame": {
    "_class": "rect",
    "constrainProportions": false,
    "do_objectID": "4EF48522-9B00-487D-B635-B8E93F121B77",
    "height": 30,
    "width": 30,
    "x": 0,
    "y": 459
  },
  "hasClippingMask": false,
  "horizontalSpacing": 0,
  "isFixedToViewport": false,
  "isFlippedHorizontal": false,
  "isFlippedVertical": false,
  "isLocked": false,
  "isVisible": true,
  "layerListExpandedType": 0,
  "name": "Icon / Edit",
  "nameIsFixed": false,
  "overrideValues": [
  ],
  "resizingConstraint": 63,
  "resizingType": 0,
  "rotation": 0,
  "scale": 1,
  "shouldBreakMaskChain": false,
  "style": {
    "_class": "style",
    "do_objectID": "F2A0A1AD-6384-47AC-A027-497D8413A297",
    "endMarkerType": 0,
    "miterLimit": 10,
    "startMarkerType": 0,
    "windingRule": 1
  },
  "symbolID": "B64C3833-601D-4F02-AB34-0B553999C549",
  "verticalSpacing": 0
}