{
  "_class": "shapeGroup",
  "booleanOperation": 3,
  "clippingMaskMode": 0,
  "do_objectID": "4C7AACD0-6A71-446C-8677-7871E06CF017",
  "exportOptions": {
    "_class": "exportOptions",
    "exportFormats": [
    ],
    "includedLayerIds": [
    ],
    "layerOptions": 0,
    "shouldTrim": false
  },
  "frame": {
    "_class": "rect",
    "constrainProportions": true,
    "height": 8.531999999999998,
    "width": 22.48657149999999,
    "x": 13.75682517439127,
    "y": 8.600000000000001
  },
  "groupLayout": {
    "_class": "MSImmutableFreeformGroupLayout"
  },
  "hasClickThrough": false,
  "hasClippingMask": false,
  "isFixedToViewport": false,
  "isFlippedHorizontal": false,
  "isFlippedVertical": false,
  "isLocked": false,
  "isVisible": true,
  "layerListExpandedType": 0,
  "layers": [
    {
      "class": "shapePath",
      "id": "A8E66A21-96DF-4E51-89BA-90636C7BAEF8"
    },
    {
      "class": "shapePath",
      "id": "96165088-9794-4FAC-97A5-E0C60677632F"
    },
    {
      "class": "shapePath",
      "id": "A87B180B-6FC8-4886-B6AF-F240EA623766"
    }
  ],
  "name": "Jun",
  "nameIsFixed": false,
  "resizingConstraint": 63,
  "resizingType": 0,
  "rotation": 0,
  "shouldBreakMaskChain": false,
  "style": {
    "_class": "style",
    "endMarkerType": 0,
    "fills": [
      {
        "_class": "fill",
        "color": {
          "_class": "color",
          "alpha": 1,
          "blue": 0.407843137254902,
          "green": 0.8,
          "red": 0.6
        },
        "fillType": 0,
        "isEnabled": true,
        "noiseIndex": 0,
        "noiseIntensity": 0,
        "patternFillType": 1,
        "patternTileScale": 1
      }
    ],
    "miterLimit": 10,
    "startMarkerType": 0,
    "windingRule": 0
  },
  "windingRule": 0
}