{
  "_class": "group",
  "booleanOperation": -1,
  "clippingMaskMode": 0,
  "do_objectID": "CF4F44D5-EB6E-4299-979D-9E3376BC4ECB",
  "exportOptions": {
    "_class": "exportOptions",
    "do_objectID": "CDFE9FB2-5436-4328-8267-07BC87A6E248",
    "exportFormats": [
    ],
    "includedLayerIds": [
    ],
    "layerOptions": 0,
    "shouldTrim": false
  },
  "frame": {
    "_class": "rect",
    "constrainProportions": false,
    "do_objectID": "9FC3AA42-D7A2-4553-858A-5550D6DBAA4F",
    "height": 60,
    "width": 60,
    "x": 157,
    "y": 427
  },
  "groupLayout": {
    "_class": "MSImmutableFreeformGroupLayout",
    "do_objectID": "5F0C026E-787B-44EB-B020-A1C8D12D3F66"
  },
  "hasClickThrough": false,
  "hasClippingMask": false,
  "isFixedToViewport": false,
  "isFlippedHorizontal": false,
  "isFlippedVertical": false,
  "isLocked": false,
  "isVisible": true,
  "layerListExpandedType": 2,
  "layers": [
    {
      "class": "shapeGroup",
      "id": "42DD3334-0C84-416E-AADC-F88DAB02E3C7"
    }
  ],
  "name": "md/checkmark-circle",
  "nameIsFixed": false,
  "resizingConstraint": 63,
  "resizingType": 0,
  "rotation": 0,
  "shouldBreakMaskChain": false,
  "style": {
    "_class": "style",
    "do_objectID": "2B522F53-E28B-40AB-A7BD-F6A436AD367E",
    "endMarkerType": 0,
    "miterLimit": 10,
    "startMarkerType": 0,
    "windingRule": 1
  }
}