{
  "_class": "group",
  "booleanOperation": -1,
  "clippingMaskMode": 0,
  "do_objectID": "7123850D-7411-43B4-A991-7EE46C3F9D31",
  "exportOptions": {
    "_class": "exportOptions",
    "exportFormats": [
    ],
    "includedLayerIds": [
    ],
    "layerOptions": 0,
    "shouldTrim": false
  },
  "frame": {
    "_class": "rect",
    "constrainProportions": true,
    "height": 106,
    "width": 202,
    "x": 79,
    "y": 90
  },
  "groupLayout": {
    "_class": "MSImmutableFreeformGroupLayout"
  },
  "hasClickThrough": false,
  "hasClippingMask": false,
  "isFixedToViewport": false,
  "isFlippedHorizontal": false,
  "isFlippedVertical": false,
  "isLocked": false,
  "isVisible": true,
  "layerListExpandedType": 1,
  "layers": [
    {
      "class": "shapePath",
      "id": "54F4CF25-E51F-4E32-91E9-15ECE72EF625"
    },
    {
      "class": "shapePath",
      "id": "5C917E79-9698-4AF7-A818-329922D87A04"
    },
    {
      "class": "shapePath",
      "id": "206650B0-6304-41B0-9A11-FB232FCB5154"
    },
    {
      "class": "shapePath",
      "id": "1B4A6C5F-7C89-43AD-8978-D9E418AF3541"
    },
    {
      "class": "shapePath",
      "id": "16D86F19-CABF-49CE-83E7-BAF97D9863B9"
    },
    {
      "class": "shapePath",
      "id": "4B6678C5-61C7-4133-8F02-FB5D29179A17"
    },
    {
      "class": "shapePath",
      "id": "FA41A70C-02C0-497D-B506-5CD371E7424E"
    },
    {
      "class": "shapePath",
      "id": "6FB46545-982D-4164-AE29-D1F93EB6FA44"
    },
    {
      "class": "shapePath",
      "id": "DB3B7C94-75E8-42A6-9B32-5E3F678FF1B5"
    },
    {
      "class": "shapePath",
      "id": "29007F02-1453-4807-B2D3-BD80DF57E445"
    },
    {
      "class": "shapePath",
      "id": "CDFC5757-EAF6-49A3-8441-1A5EAE29670A"
    },
    {
      "class": "shapePath",
      "id": "6D5AF7FF-547E-468E-977E-72063D6DA04D"
    },
    {
      "class": "shapePath",
      "id": "B7118DE3-AE49-4151-93E4-C7F92970DBFC"
    },
    {
      "class": "shapePath",
      "id": "5876FEF5-E8EE-45D4-9650-91F1A7A80AFD"
    }
  ],
  "name": "lumitylogo largeblue",
  "nameIsFixed": false,
  "resizingConstraint": 63,
  "resizingType": 0,
  "rotation": 0,
  "shouldBreakMaskChain": false,
  "style": {
    "_class": "style",
    "endMarkerType": 0,
    "miterLimit": 10,
    "startMarkerType": 0,
    "windingRule": 1
  }
}