{
  "_class": "shapeGroup",
  "booleanOperation": -1,
  "clippingMaskMode": 0,
  "do_objectID": "2C4EABFF-87FF-4AAC-B49D-5AAF0242C99E",
  "exportOptions": {
    "_class": "exportOptions",
    "do_objectID": "8B3CAE55-E8EB-467B-9C93-2C93309C7405",
    "exportFormats": [
    ],
    "includedLayerIds": [
    ],
    "layerOptions": 0,
    "shouldTrim": false
  },
  "frame": {
    "_class": "rect",
    "constrainProportions": true,
    "do_objectID": "3CFEEC94-5F5E-4070-8868-031C845F3C12",
    "height": 40,
    "width": 46.67708333333334,
    "x": 1.4210854715202e-14,
    "y": 0
  },
  "groupLayout": {
    "_class": "MSImmutableFreeformGroupLayout",
    "do_objectID": "57142194-B3AA-4EAF-9410-8882F7D8FB00"
  },
  "hasClickThrough": false,
  "hasClippingMask": false,
  "isFixedToViewport": false,
  "isFlippedHorizontal": false,
  "isFlippedVertical": false,
  "isLocked": false,
  "isVisible": true,
  "layerListExpandedType": 1,
  "layers": [
    {
      "class": "shapePath",
      "id": "74878DC1-E5E1-4844-824F-8109B984CDBF"
    },
    {
      "class": "shapePath",
      "id": "3ABCD123-D6C6-49F0-9528-07CD59FA84DB"
    },
    {
      "class": "shapePath",
      "id": "4CEC6756-EC94-4344-9B21-8736B0335686"
    },
    {
      "class": "shapePath",
      "id": "E3F44A88-A289-4C56-888C-E1DAA783FC1B"
    }
  ],
  "name": "Shape",
  "nameIsFixed": false,
  "resizingConstraint": 63,
  "resizingType": 0,
  "rotation": 0,
  "shouldBreakMaskChain": false,
  "style": {
    "_class": "style",
    "do_objectID": "63DA71D8-994A-483A-8E87-DDE08B7CDB24",
    "endMarkerType": 0,
    "fills": [
      {
        "_class": "fill",
        "color": {
          "_class": "color",
          "alpha": 1,
          "blue": 0.6666666666666666,
          "green": 0.3490196078431372,
          "red": 0
        },
        "fillType": 0,
        "isEnabled": true,
        "noiseIndex": 0,
        "noiseIntensity": 0,
        "patternFillType": 1,
        "patternTileScale": 1
      }
    ],
    "miterLimit": 10,
    "startMarkerType": 0,
    "windingRule": 0
  },
  "windingRule": 0
}