{
  "_class": "MSImmutableHotspotLayer",
  "booleanOperation": -1,
  "do_objectID": "841F5CB4-FF82-482A-BC7F-1C78E4B4B873",
  "exportOptions": {
    "_class": "exportOptions",
    "exportFormats": [
    ],
    "includedLayerIds": [
    ],
    "layerOptions": 0,
    "shouldTrim": false
  },
  "flow": {
    "_class": "MSImmutableFlowConnection",
    "animationType": 2,
    "destinationArtboardID": "E0489265-DCB5-47A3-B542-F07A396B3887",
    "do_objectID": "66571E8C-24D6-4733-9C0F-6F075551A4F0"
  },
  "frame": {
    "_class": "rect",
    "constrainProportions": false,
    "height": 53,
    "width": 61,
    "x": 314,
    "y": 44
  },
  "isFixedToViewport": false,
  "isFlippedHorizontal": false,
  "isFlippedVertical": false,
  "isLocked": false,
  "isVisible": true,
  "layerListExpandedType": 0,
  "name": "Hotspot",
  "nameIsFixed": false,
  "resizingConstraint": 63,
  "resizingType": 0,
  "rotation": 0,
  "shouldBreakMaskChain": false
}