{
  "_class": "group",
  "booleanOperation": -1,
  "clippingMaskMode": 0,
  "do_objectID": "DFCFB45E-CFA3-4A39-AB68-04C78C8F9AEA",
  "exportOptions": {
    "_class": "exportOptions",
    "do_objectID": "4466DED7-7337-4A6F-97BE-55CB88C5AE17",
    "exportFormats": [
    ],
    "includedLayerIds": [
    ],
    "layerOptions": 0,
    "shouldTrim": false
  },
  "frame": {
    "_class": "rect",
    "constrainProportions": true,
    "do_objectID": "4D9A5C33-4817-4394-BB69-3DAE0B12AAD9",
    "height": 36,
    "width": 36,
    "x": 1560,
    "y": 176
  },
  "groupLayout": {
    "_class": "MSImmutableFreeformGroupLayout",
    "do_objectID": "B4C442E9-47A9-44C9-AA60-4E2DD2482647"
  },
  "hasClickThrough": false,
  "hasClippingMask": false,
  "isFixedToViewport": false,
  "isFlippedHorizontal": false,
  "isFlippedVertical": false,
  "isLocked": false,
  "isVisible": true,
  "layerListExpandedType": 2,
  "layers": [
    {
      "class": "shapeGroup",
      "id": "82F1EC46-36D4-4160-8ABE-8F30DB9FA107"
    }
  ],
  "name": "md/create",
  "nameIsFixed": false,
  "resizingConstraint": 63,
  "resizingType": 0,
  "rotation": 0,
  "shouldBreakMaskChain": false,
  "style": {
    "_class": "style",
    "do_objectID": "04EFB7D3-3CC6-44EC-9C8B-CE15589106A7",
    "endMarkerType": 0,
    "miterLimit": 10,
    "startMarkerType": 0,
    "windingRule": 1
  }
}